winbrew/__init__.py
winbrew/config.py
winbrew/execute.py
winbrew/execute.py.bak
winbrew/formula.py
winbrew/formula.py.bak
winbrew/manifest.py
winbrew/util.py
winbrew-1.2.3.dist-info/LICENSE
winbrew-1.2.3.dist-info/METADATA
winbrew-1.2.3.dist-info/WHEEL
winbrew-1.2.3.dist-info/entry_points.txt
winbrew-1.2.3.dist-info/pbr.json
winbrew-1.2.3.dist-info/top_level.txt
winbrew-1.2.3.dist-info/RECORD
